table_cls/__init__.py
table_cls/main.py
table_cls/utils/__init__.py
table_cls/utils/download_model.py
table_cls/utils/logger.py
table_cls/utils/utils.py
table_cls-1.2.0.dist-info/LICENSE
table_cls-1.2.0.dist-info/METADATA
table_cls-1.2.0.dist-info/WHEEL
table_cls-1.2.0.dist-info/top_level.txt
table_cls-1.2.0.dist-info/RECORD
